chama/__init__.py
chama/graphics.py
chama/impact.py
chama/optimize.py
chama/sensors.py
chama/simulation.py
chama/utils.py
chama/tests/data/Net3_ec.impact
chama/tests/data/signals.csv
chama-0.3.0.dist-info/LICENSE.txt
chama-0.3.0.dist-info/METADATA
chama-0.3.0.dist-info/WHEEL
chama-0.3.0.dist-info/top_level.txt
chama-0.3.0.dist-info/RECORD
