Metadata-Version: 2.1
Name: chama
Version: 0.3.0
Summary: Sensor Placement Optimization.
Home-page: https://github.com/sandialabs/chama
Author: Chama developers
Maintainer-email: kaklise@sandia.gov
License: Revised BSD
License-File: LICENSE.txt
Requires-Dist: pyomo
Requires-Dist: pandas
Requires-Dist: numpy
Requires-Dist: scipy
